{
  "TODO-key": {
    "title": { "enUS": "Dispute of the answer", "zhHK": "TODO: placeholder", "zhCN": "TODO: placeholder" },
    "content": {
      "enUS": "If you believe the explanation or answer is incorrect or incomplete, please show us your teacher's result, we will have a third person to verify (at our cost). Based on the verification, partial refund. <strong>If student dedicates questions to a specific tutor, there will be NO refund.</strong>",
      "zhHK": "TODO: placeholder",
      "zhCN": "TODO: placeholder"
    }
  }
}
